odoo10_addon_report_xlsx_helper-10.0.1.0.0.99.dev10-py2.7-nspkg.pth
odoo/addons/report_xlsx_helper/README.rst
odoo/addons/report_xlsx_helper/__init__.py
odoo/addons/report_xlsx_helper/__manifest__.py
odoo/addons/report_xlsx_helper/i18n/report_xlsx_helper.pot
odoo/addons/report_xlsx_helper/report/__init__.py
odoo/addons/report_xlsx_helper/report/abstract_report_xlsx.py
odoo/addons/report_xlsx_helper/static/description/icon.png
odoo/addons/report_xlsx_helper/tests/__init__.py
odoo/addons/report_xlsx_helper/tests/test_partner_report_xlsx.py
odoo/addons/report_xlsx_helper/tests/test_report_xlsx_helper.py
odoo10_addon_report_xlsx_helper-10.0.1.0.0.99.dev10.dist-info/METADATA
odoo10_addon_report_xlsx_helper-10.0.1.0.0.99.dev10.dist-info/RECORD
odoo10_addon_report_xlsx_helper-10.0.1.0.0.99.dev10.dist-info/WHEEL
odoo10_addon_report_xlsx_helper-10.0.1.0.0.99.dev10.dist-info/namespace_packages.txt
odoo10_addon_report_xlsx_helper-10.0.1.0.0.99.dev10.dist-info/top_level.txt
