Metadata-Version: 2.1
Name: odoo10-addon-report-xlsx-helper
Version: 10.0.1.0.0.99.dev10
Summary: Report xlsx helpers
Home-page: https://github.com/OCA/reporting-engine
Author: Noviat,Odoo Community Association (OCA)
Author-email: support@odoo-community.org
License: AGPL-3
Platform: UNKNOWN
Classifier: Programming Language :: Python
Classifier: Framework :: Odoo
Classifier: License :: OSI Approved :: GNU Affero General Public License v3
Requires-Python: ~=2.7
Requires-Dist: odoo10-addon-report-xlsx
Requires-Dist: odoo (<10.1dev,>=10.0)
Requires-Dist: xlsxwriter
